datecalc/__init__.py
datecalc/__main__.py
datecalc/cli.py
datecalc/gui.py
datecalc/utils.py
datecalc-0.2.1.data/data/share/applications/datecalc.desktop
datecalc-0.2.1.dist-info/DESCRIPTION.rst
datecalc-0.2.1.dist-info/METADATA
datecalc-0.2.1.dist-info/RECORD
datecalc-0.2.1.dist-info/WHEEL
datecalc-0.2.1.dist-info/entry_points.txt
datecalc-0.2.1.dist-info/metadata.json
datecalc-0.2.1.dist-info/top_level.txt
